setup.py
retroactive/__init__.py
retroactive/dispatcher.py
retroactive/examples.py
retroactive/full_retroactivity.py
retroactive.egg-info/PKG-INFO
retroactive.egg-info/SOURCES.txt
retroactive.egg-info/dependency_links.txt
retroactive.egg-info/not-zip-safe
retroactive.egg-info/top_level.txt
retroactive/basic/__init__.py
retroactive/basic/bst.py
retroactive/basic/link_cut_tree.py
retroactive/basic/modified_ab_tree.py
retroactive/basic/names.py
retroactive/basic/queue.py
retroactive/full/__init__.py
retroactive/full/deque.py
retroactive/full/union_find.py
retroactive/partial/__init__.py
retroactive/partial/general_transform.py
retroactive/partial/priority_queue.py
retroactive/partial/queue.py
retroactive/partial/sdps.py